Metadata-Version: 1.1
Name: egn
Version: 0.1.3
Summary: Validator, generator and parser for Bulgarian unique citizenship numbers (EGN/ЕГН).
Home-page: http://github.com/miglen/egn/
Author: Miglen Evlogiev
Author-email: github@miglen.com
License: GPL-3.0
Platform: UNKNOWN
Classifier: Development Status :: 3 - Alpha
Classifier: Intended Audience :: Developers
Classifier: License :: OSI Approved :: GNU General Public License v3 or later (GPLv3+)
Classifier: Operating System :: OS Independent
Classifier: Programming Language :: Python
Classifier: Programming Language :: Python :: 2
Classifier: Programming Language :: Python :: 2.7
Classifier: Programming Language :: Python :: 3
Classifier: Programming Language :: Python :: 3.3
Classifier: Programming Language :: Python :: 3.4
Classifier: Programming Language :: Python :: 3.5
